compile_minifier/__init__.py
compile_minifier/main.py
compile_minifier-0.2.2.dist-info/METADATA
compile_minifier-0.2.2.dist-info/WHEEL
compile_minifier-0.2.2.dist-info/entry_points.txt
compile_minifier-0.2.2.dist-info/RECORD
