Metadata-Version: 2.1
Name: compile-minifier
Version: 0.2.2
Summary: Python compiler and minifier
License: MIT
Author: Amoki
Author-email: hugo@bimdata.io
Requires-Python: >=3.5,<3.14
Classifier: License :: OSI Approved :: MIT License
Classifier: Programming Language :: Python :: 3
Classifier: Programming Language :: Python :: 3.5
Classifier: Programming Language :: Python :: 3.6
Classifier: Programming Language :: Python :: 3.7
Classifier: Programming Language :: Python :: 3.8
Classifier: Programming Language :: Python :: 3.9
Classifier: Programming Language :: Python :: 3.10
Classifier: Programming Language :: Python :: 3.11
Classifier: Programming Language :: Python :: 3.12
Classifier: Programming Language :: Python :: 3.13
Requires-Dist: fire (>=0.7.0,<0.8.0)
Requires-Dist: python-minifier (>=2.11.3,<3.0.0)
Project-URL: homepage, https://github.com/bimdata/compile-minifier
Project-URL: repository, https://github.com/bimdata/compile-minifier
